disallow_import_star/__about__.py
disallow_import_star/__init__.py
disallow_import_star-0.4.1.dist-info/METADATA
disallow_import_star-0.4.1.dist-info/WHEEL
disallow_import_star-0.4.1.dist-info/licenses/LICENSE.txt
disallow_import_star-0.4.1.dist-info/RECORD
