Metadata-Version: 2.1
Name: disallow-import-star
Version: 0.4.1
Project-URL: Documentation, https://github.com/treyhunner/disallow-import-star#readme
Project-URL: Issues, https://github.com/treyhunner/disallow-import-star/issues
Project-URL: Source, https://github.com/treyhunner/disallow-import-star
Author-email: Trey Hunner <trey@treyhunner.com>
License-Expression: MIT
License-File: LICENSE.txt
Classifier: Development Status :: 4 - Beta
Classifier: Programming Language :: Python
Classifier: Programming Language :: Python :: 3.7
Classifier: Programming Language :: Python :: 3.8
Classifier: Programming Language :: Python :: 3.9
Classifier: Programming Language :: Python :: 3.10
Classifier: Programming Language :: Python :: 3.11
Classifier: Programming Language :: Python :: Implementation :: CPython
Classifier: Programming Language :: Python :: Implementation :: PyPy
Requires-Python: >=3.7
